py2factor/__init__.py
py2factor/_compat.py
py2factor/add.py
py2factor/delete.py
py2factor/list.py
py2factor/main.py
py2factor/profile.py
py2factor/profiles.py
py2factor/store.py
py2factor/totp.py
py2factor/version.py
py2factor-0.1.2.dist-info/DESCRIPTION.rst
py2factor-0.1.2.dist-info/METADATA
py2factor-0.1.2.dist-info/RECORD
py2factor-0.1.2.dist-info/WHEEL
py2factor-0.1.2.dist-info/entry_points.txt
py2factor-0.1.2.dist-info/metadata.json
py2factor-0.1.2.dist-info/namespace_packages.txt
py2factor-0.1.2.dist-info/top_level.txt
