Metadata-Version: 2.0
Name: py2factor
Version: 0.1.2
Summary: 2Factor authention app
Home-page: https://github.com/sarathsp06/py2factor
Author: Sarath Sadasivan Pillai
Author-email: sarathsp06@gmail.com
License: UNKNOWN
Download-URL: https://github.com/sarathsp06/py2factor/tarball/master
Platform: linux
Classifier: Development Status :: 3 - Alpha
Classifier: License :: OSI Approved :: Apache Software License
Classifier: Programming Language :: Python
Classifier: Programming Language :: Python :: 2
Classifier: Programming Language :: Python :: 2.7
Classifier: Programming Language :: Python :: 3
Classifier: Programming Language :: Python :: 3.2
Classifier: Environment :: Console
Requires-Dist: cliff
